{"dependencies":[{"name":"/home/nick/Desktop/Code/Learn-Redux-Starter-Files/test-app/node_modules/react-dom/package.json","includedInParent":true,"mtime":1530981824985},{"name":"/home/nick/Desktop/Code/Learn-Redux-Starter-Files/test-app/package.json","includedInParent":true,"mtime":1530984832683},{"name":"/home/nick/Desktop/Code/Learn-Redux-Starter-Files/test-app/.babelrc","includedInParent":true,"mtime":1530987324534},{"name":"./validateDOMNesting","loc":{"line":11,"column":33},"parent":"/home/nick/Desktop/Code/Learn-Redux-Starter-Files/test-app/node_modules/react-dom/lib/ReactDOMContainerInfo.js","resolved":"/home/nick/Desktop/Code/Learn-Redux-Starter-Files/test-app/node_modules/react-dom/lib/validateDOMNesting.js"}],"generated":{"js":"/**\n * Copyright (c) 2013-present, Facebook, Inc.\n *\n * This source code is licensed under the MIT license found in the\n * LICENSE file in the root directory of this source tree.\n *\n */\n\n'use strict';\n\nvar validateDOMNesting = require('./validateDOMNesting');\n\nvar DOC_NODE_TYPE = 9;\n\nfunction ReactDOMContainerInfo(topLevelWrapper, node) {\n  var info = {\n    _topLevelWrapper: topLevelWrapper,\n    _idCounter: 1,\n    _ownerDocument: node ? node.nodeType === DOC_NODE_TYPE ? node : node.ownerDocument : null,\n    _node: node,\n    _tag: node ? node.nodeName.toLowerCase() : null,\n    _namespaceURI: node ? node.namespaceURI : null\n  };\n  if (undefined !== 'production') {\n    info._ancestorInfo = node ? validateDOMNesting.updatedAncestorInfo(null, info._tag, null) : null;\n  }\n  return info;\n}\n\nmodule.exports = ReactDOMContainerInfo;","map":null},"hash":"785cd8180c2621e3c335f4ed497dc33a","cacheData":{"env":{}},"id":482}